<?xml version="1.0" encoding="UTF-8"?>
<!DOCTYPE suite SYSTEM "http://testng.org/testng-1.0.dtd">
<suite name="Failed suite [CreateUserForForgotPassword]">
  <test name="CreateUserForForgotPassword(failed)">
    <classes>
      <class name="com.edureka.registration.CreateUserForForgotPassword">
        <methods>
          <include name="setUp"/>
          <include name="test_CreateUserForForgotPassword"/>
          <include name="tearDown"/>
        </methods>
      </class> <!-- com.edureka.registration.CreateUserForForgotPassword -->
    </classes>
  </test> <!-- CreateUserForForgotPassword(failed) -->
</suite> <!-- Failed suite [CreateUserForForgotPassword] -->
